{
  "type": "raster",
  "id": "ts_kaikoura-earthquake-2016-0.2m",
  "name": "kaikoura-earthquake-2016-0.2m",
  "title": "Kaikōura Earthquake 0.2m Aerial Photos (2016)",
  "background": {
    "r": 0,
    "g": 0,
    "b": 0,
    "alpha": 0
  },
  "category": "Event",
  "layers": [
    {
      "2193": "s3://linz-basemaps/2193/kaikoura-earthquake_2016_0.2m/01KRM9ZSCBYJG0PXGBW36ASSCN/",
      "3857": "s3://linz-basemaps/3857/kaikoura-earthquake_2016_0.2m/01KRM9Z7YA5XJNMQKXE5E4B3VT/",
      "name": "kaikoura-earthquake-2016-0.2m",
      "title": "Kaikōura Earthquake 0.2m Aerial Photos (2016)",
      "category": "Event",
      "minZoom": 0,
      "maxZoom": 32
    }
  ]
}
